tests/__init__.py
tests/interpretation/__init__.py
tests/interpretation/assets/utils.py
tests/interpretation/example_level/__init__.py
tests/interpretation/example_level/test_feature_similarity.py
tests/interpretation/example_level/test_gradient_similarity.py
tests/interpretation/example_level/test_reppoint.py
trustai/.gitignore
trustai/__init__.py
trustai/application/README.md
trustai/demo/__init__.py
trustai/demo/demo.py
trustai/demo/utils.py
trustai/evaluation/README.md
trustai/evaluation/__init__.py
trustai/evaluation/evaluator.py
trustai/interpretation/__init__.py
trustai/interpretation/base_interpret.py
trustai/interpretation/python_utils.py
trustai/interpretation/example_level/README.md
trustai/interpretation/example_level/__init__.py
trustai/interpretation/example_level/common/__init__.py
trustai/interpretation/example_level/common/data_class.py
trustai/interpretation/example_level/common/utils.py
trustai/interpretation/example_level/method/__init__.py
trustai/interpretation/example_level/method/example_base_interpreter.py
trustai/interpretation/example_level/method/feature_similarity.py
trustai/interpretation/example_level/method/gradient_similarity.py
trustai/interpretation/example_level/method/representer_point.py
trustai/interpretation/example_level/method/tmp.py
trustai/interpretation/token_level/README.md
trustai/interpretation/token_level/__init__.py
trustai/interpretation/token_level/common/__init__.py
trustai/interpretation/token_level/common/postprocess_attribution.py
trustai/interpretation/token_level/common/predict_functions.py
trustai/interpretation/token_level/data_processor/__init__.py
trustai/interpretation/token_level/data_processor/data_class.py
trustai/interpretation/token_level/data_processor/visualizer.py
trustai/interpretation/token_level/method/__init__.py
trustai/interpretation/token_level/method/attention.py
trustai/interpretation/token_level/method/base_interpret.py
trustai/interpretation/token_level/method/gradient_shap.py
trustai-0.1.12.dist-info/LICENSE
trustai-0.1.12.dist-info/METADATA
trustai-0.1.12.dist-info/WHEEL
trustai-0.1.12.dist-info/top_level.txt
trustai-0.1.12.dist-info/RECORD
