Metadata-Version: 2.1
Name: trustai
Version: 0.1.12
Summary: baidu TrustAI
Home-page: https://github.com/PaddlePaddle/TrustAI
Author: Baidu NLP
Author-email: nlp-parser@baidu.com
License: Apache License 2.0
Keywords: baidu,TrustAI,interpretation
Classifier: Programming Language :: Python :: 3
Classifier: Programming Language :: Python :: 3.6
Classifier: Programming Language :: Python :: 3.7
Classifier: Programming Language :: Python :: 3.8
Classifier: License :: OSI Approved :: Apache Software License
Classifier: Operating System :: OS Independent
License-File: LICENSE
Requires-Dist: scikit-learn
Requires-Dist: numpy
Requires-Dist: tqdm
Requires-Dist: matplotlib
Requires-Dist: IPython
